{
  "id": "membership-account__membership-billing",
  "path": [
    "membership-account",
    "membership-billing"
  ],
  "sourceUrl": "https://raleighhillsbusinessassn.org/membership-account/membership-billing/",
  "title": "Log In | Raleigh Hills Business Association",
  "description": "",
  "htmlMain": "<div class=\"pmpro\">\n\t\t<section id=\"pmpro_login\" class=\"pmpro_section\">\n\t\t\t\t\t\t\t\t\t\t<div class=\"pmpro_card pmpro_login_wrap\">\n\t\t\t\t\t\t\t\t\t\t\t\t\t\t\t\t<div class=\"pmpro_card_content\">\n\t\t\t\t\t\t\t\t\t\t<div class=\"pmpro_form_field-password-toggle\">\n\t\t<button type=\"button\" id=\"pmpro_btn-password-toggle-1\" class=\"pmpro_btn pmpro_btn-plain hide-if-no-js\" data-toggle=\"0\">\n\t\t\t<span class=\"pmpro_icon pmpro_icon-eye\" aria-hidden=\"true\"><svg xmlns=\"http://www.w3.org/2000/svg\" width=\"20\" height=\"20\" viewBox=\"0 0 24 24\" fill=\"none\" stroke=\"var(--pmpro--color--accent)\" stroke-width=\"2\" stroke-linecap=\"round\" stroke-linejoin=\"round\" class=\"feather feather-eye\"><path d=\"M1 12s4-8 11-8 11 8 11 8-4 8-11 8-11-8-11-8z\"></path><circle cx=\"12\" cy=\"12\" r=\"3\"></circle></svg></span>\n\t\t\t<span class=\"pmpro_form_field-password-toggle-state\">Show Password</span>\n\t\t</button>\n\t</div>\n\t\n\t\t\t\t\t\t\t\t\t</div> <!-- end pmpro_card_content -->\n\t\t\t\t\t\t\t\t<div class=\"pmpro_card_actions\">\n\t\t\t\t\t\t\t\t\t\t<div class=\"pmpro_actions_nav\">\n\t\t<a href=\"https://raleighhillsbusinessassn.org/login/?action=reset_pass\">Lost Password?</a>\t</div> <!-- end pmpro_actions_nav -->\n\t\t\t\t\t\t\t\t\t</div> <!-- end pmpro_card_actions -->\n\t\t\t\t\t\t\t</div> <!-- end pmpro_login_wrap -->\n\t\t\t\t\t\t\t\t\t\t\t\t\t\t\n\t\t\t\t\t\t\t\n\t\t\t\t\t\t\t\t\t</section> <!-- end pmpro_login -->\n\t</div> <!-- end pmpro -->\n\t\n\t"
}